semnet/__init__.py
semnet/semnet.py
semnet-0.1.3.dist-info/licenses/LICENSE
semnet-0.1.3.dist-info/METADATA
semnet-0.1.3.dist-info/WHEEL
semnet-0.1.3.dist-info/top_level.txt
semnet-0.1.3.dist-info/RECORD
