Metadata-Version: 2.4
Name: semnet
Version: 0.1.3
Summary: Semantic Networks from Embeddings
Author-email: Ian Goodrich <ian@igdr.ch>
License: MIT
Project-URL: Homepage, https://github.com/specialprocedures/semnet
Project-URL: Documentation, https://semnetdocs.readthedocs.io
Project-URL: Repository, https://github.com/specialprocedures/semnet
Project-URL: Bug Tracker, https://github.com/specialprocedures/semnet/issues
Keywords: semantic networks,embeddings,graph analysis,nlp,similarity,networkx
Classifier: Development Status :: 4 - Beta
Classifier: Intended Audience :: Developers
Classifier: Intended Audience :: Science/Research
Classifier: License :: OSI Approved :: MIT License
Classifier: Operating System :: OS Independent
Classifier: Programming Language :: Python :: 3
Classifier: Programming Language :: Python :: 3.8
Classifier: Programming Language :: Python :: 3.9
Classifier: Programming Language :: Python :: 3.10
Classifier: Programming Language :: Python :: 3.11
Classifier: Programming Language :: Python :: 3.12
Classifier: Programming Language :: Python :: 3.13
Classifier: Topic :: Scientific/Engineering :: Artificial Intelligence
Classifier: Topic :: Software Development :: Libraries :: Python Modules
Requires-Python: >=3.8
License-File: LICENSE
Requires-Dist: networkx>=2.5
Requires-Dist: annoy>=1.17.0
Requires-Dist: numpy>=1.19.0
Requires-Dist: pandas>=1.2.0
Requires-Dist: tqdm>=4.60.0
Provides-Extra: dev
Requires-Dist: pytest>=6.0; extra == "dev"
Requires-Dist: pytest-cov>=2.10; extra == "dev"
Requires-Dist: black>=21.0; extra == "dev"
Requires-Dist: isort>=5.0; extra == "dev"
Requires-Dist: flake8>=3.8; extra == "dev"
Requires-Dist: mypy>=0.800; extra == "dev"
Requires-Dist: sentence-transformers>=2.0.0; extra == "dev"
Provides-Extra: docs
Requires-Dist: sphinx>=4.0; extra == "docs"
Requires-Dist: sphinx-rtd-theme>=1.0; extra == "docs"
Requires-Dist: myst-parser>=0.17; extra == "docs"
Provides-Extra: examples
Requires-Dist: sentence-transformers>=2.0.0; extra == "examples"
Requires-Dist: matplotlib>=3.3.0; extra == "examples"
Requires-Dist: jupyter>=1.0.0; extra == "examples"
Dynamic: license-file
